nyt_games/__init__.py
nyt_games/exceptions.py
nyt_games/models.py
nyt_games/nyt_games.py
nyt_games/py.typed
nyt_games-0.5.0.dist-info/LICENSE.md
nyt_games-0.5.0.dist-info/METADATA
nyt_games-0.5.0.dist-info/WHEEL
nyt_games-0.5.0.dist-info/RECORD
